ipynbparser/__init__.py
ipynbparser-0.0.1.dist-info/METADATA
ipynbparser-0.0.1.dist-info/WHEEL
ipynbparser-0.0.1.dist-info/RECORD
